Workbook

Sheet TestPlan
A1: Test Plan ID | B1: ParaBank_01
A2: Application Name | B2: ParaBank (Online Banking)
A3: Application URL | B3: https://parabank.parasoft.com/parabank/index.htm
A4: Application Type | B4: Web Application
A5: Testing Type | B5: Manual Testing
A6: Testing Approach | B6: Black Box Testing
A7: In Scope | B7: Registration, Login, Forgot Login Info, Accounts Overview, Open New Account, Transfer Funds, Bill Pay, Find Transactions, Update Contact Info, Request Loan, Logout, Session Security
A8: Out of Scope | B8: Admin page, SOAP/REST web services, Performance and load testing
A9: Test Objectives | B9: Verify that the main online banking functions work correctly and identify defects.
A10: Test Environment | B10: Windows 11, Google Chrome, Internet
A11: Entry Criteria | B11: Application URL is accessible, test environment is ready, and a registered test user is available.
A12: Exit Criteria | B12: All planned test cases are executed and critical defects are reported and tracked.
... A16: Prepared By | B16: Gautami Mahajan

Sheet TestScenario
A1: S.No | B1: Module | C1: Test Scenario
A2: 1 | B2: Registration | C2: Verify that a new user can register successfully with valid details.
A3: 2 | B3: Registration | C3: Verify that validation messages are displayed when all registration fields are left blank.
A4: 3 | B4: Registration | C4: Verify that registration fails when Password and Confirm Password do not match.
A5: 4 | B5: Registration | C5: Verify that registration fails when the username already exists.
A6: 5 | B6: Registration | C6: Verify that Username is mandatory on the Register page.
A7: 6 | B7: Login | C7: Verify that the user can log in successfully with valid credentials.
A8: 7 | B8: Login | C8: Verify that an error is displayed when an invalid username and password are entered.
A9: 8 | B9: Login | C9: Verify that an error is displayed when Username and Password are left blank.
A10: 9 | B10: Login | C10: Verify that the Password field masks the entered characters.
A11: 10 | B11: Login | C11: Verify that a registered user can retrieve login info using the Forgot login info link.
A12: 11 | B12: Login | C12: Verify that validation messages are displayed on the Forgot login info page when fields are blank.
A13: 12 | B13: Security | C13: Verify that the session ID is not exposed in the page URL.
... A37: 36 | B37: Logout | C37: Verify that the user can log in again after logout.

Sheet TestCase
A1: S.No | B1: Test Case ID | C1: Module | D1: Test Scenario | E1: Test Steps | F1: Test Data | G1: Expected Result | H1: Actual Result | I1: Status | J1: Bug ID
A2: 1 | B2: TC_001 | C2: Registration | D2: Verify that a new user can register successfully with valid details. | E2: 1. Open https://parabank.parasoft.com/parabank/index.htm. 2. Click Register. 3. Enter all details. 4. Click Register. | F2: First Name: John Last Name: Test Address: 12 MG Road City: Mumbai State: Maharashtra Zip Code: 400001 Phone: 9876543210 SSN: 123-45-6789 Username: <new unique username> Password: Test@123 Confirm: Test@123 | G2: Account should be created and the message "Your account was created successfully. You are now logged in." should be displayed. | H2: Account was created, welcome message was displayed and the user was logged in. | I2: Pass
A3: 2 | B3: TC_002 | C3: Registration | D3: Verify that validation messages are displayed when all registration fields are left blank. | E3: 1. Open the Register page. 2. Leave all fields blank. 3. Click Register. | F3: All fields blank | G3: Required-field messages (e.g. "First name is required.") should be displayed for all mandatory fields. | H3: Required-field messages were displayed for all mandatory fields. | I3: Pass
A4: 3 | B4: TC_003 | C4: Registration | D4: Verify that registration fails when Password and Confirm Password do not match. | E4: 1. Open the Register page. 2. Fill all fields with different Password and Confirm values. 3. Click Register. | F4: Password: Test@123 Confirm: Test@456 | G4: Message "Passwords did not match." should be displayed. | H4: Message "Passwords did not match." was displayed. | I4: Pass
A5: 4 | B5: TC_004 | C5: Registration | D5: Verify that registration fails when the username already exists. | E5: 1. Open the Register page. 2. Fill all fields using an existing username. 3. Click Register. | F5: Username: <your registered username> (already registered) | G5: Message "This username already exists." should be displayed. | H5: Message "This username already exists." was displayed. | I5: Pass
A6: 5 | B6: TC_005 | C6: Registration | D6: Verify that Username is mandatory on the Register page. | E6: 1. Open the Register page. 2. Fill all fields except Username. 3. Click Register. | F6: Username: Blank | G6: Message "Username is required." should be displayed. | H6: Message "Username is required." was displayed. | I6: Pass
A7: 6 | B7: TC_006 | C7: Login | D7: Verify that the user can log in successfully with valid credentials. | E7: 1. Open the application. 2. Enter username and password. 3. Click Log In. | F7: Username: <your registered username> Password: <your password> | G7: User should log in and the Accounts Overview page should open. | H7: Accounts Overview page was displayed. | I7: Pass
A8: 7 | B8: TC_007 | C8: Login | D8: Verify that an error is displayed when an invalid username and password are entered. | E8: 1. Open the application. 2. Enter invalid username and password. 3. Click Log In. | F8: Username: wrong_user Password: wrong123 | G8: Error "The username and password could not be verified." should be displayed. | H8: Error message was displayed and the user was not logged in. | I8: Pass
A9: 8 | B9: TC_008 | C9: Login | D9: Verify that an error is displayed when Username and Password are left blank. | E9: 1. Open the application. 2. Leave both fields blank. 3. Click Log In. | F9: Username: Blank Password: Blank | G9: Message "Please enter a username and password." should be displayed. | H9: Message "Please enter a username and password." was displayed. | I9: Pass
A10: 9 | B10: TC_009 | C10: Login | D10: Verify that the Password field masks the entered characters. | E10: 1. Open the application. 2. Type text in the Password field. | F10: Password: <your password> | G10: Password characters should be masked. | H10: Password characters were masked. | I10: Pass
A11: 10 | B11: TC_010 | C11: Login | D11: Verify that a registered user can retrieve login info using the Forgot login info link. | E11: 1. Click "Forgot login info?". 2. Enter the details used at registration. 3. Click Find My Login Info. | F11: First Name, Last Name, Address, City, State, Zip Code, SSN used at registration | G11: Username and password of the user should be displayed. | H11: Login information was displayed for the matching customer. | I11: Pass
A12: 11 | B12: TC_011 | C12: Login | D12: Verify that validation messages are displayed on the Forgot login info page when fields are blank. | E12: 1. Click "Forgot login info?". 2. Leave all fields blank. 3. Click Find My Login Info. | F12: All fields blank | G12: Required-field messages should be displayed. | H12: Required-field messages were displayed. | I12: Pass
A13: 12 | B13: TC_012 | C13: Security | D13: Verify that the session ID is not exposed in the page URL. | E13: 1. Open https://parabank.parasoft.com/parabank/index.htm. 2. Click any link (e.g. About Us or Register). 3. Check the browser address bar / link URLs. | F13: Pages: Home, About Us, Register | G13: URLs should not contain the session ID (no ";jsessionid=" in the URL). | H13: Page links and URLs contain the session ID (";jsessionid=...") which exposes the session identifier. | I13: Fail | J13: BUG_001
A14: 13 | B14: TC_013 | C14: Security | D14: Verify that the user cannot access account pages using the browser Back button after logout. | E14: 1. Login. 2. Click Log Out. 3. Click the browser Back button. | F14: Username: <your registered username> Password: <your password> | G14: Session should be invalid and the user should not see account data. | H14: User was able to view cached account pages using browser Back button after logout. | I14: Fail | J14: BUG_002
A15: 14 | B15: TC_014 | C15: Accounts Overview | D15: Verify that Accounts Overview lists all accounts with balance and available amount. | E15: 1. Login. 2. Open Accounts Overview. | F15: Username: <your registered username> Password: <your password> | G15: Account numbers, balances, available amounts and a total should be displayed. | H15: Accounts, balances, available amounts and the total were displayed. | I15: Pass
A16: 15 | B16: TC_015 | C16: Accounts Overview | D16: Verify that the Account Details page opens when an account number is clicked. | E16: 1. Login. 2. Open Accounts Overview. 3. Click an account number. | F16: Account: any listed account | G16: Account Details page should open with account type, balance and activity. | H16: Account Details page was displayed. | I16: Pass
A17: 16 | B17: TC_016 | C17: Open New Account | D17: Verify that a new Checking account can be opened. | E17: 1. Login. 2. Click Open New Account. 3. Select CHECKING. 4. Select an existing account to fund it. 5. Click Open New Account. | F17: Type: CHECKING | G17: Message "Account Opened!" with the new account number should be displayed. | H17: "Account Opened!" and a new account number were displayed. | I17: Pass
A18: 17 | B18: TC_017 | C18: Open New Account | D18: Verify that a new Savings account can be opened. | E18: 1. Login. 2. Click Open New Account. 3. Select SAVINGS. 4. Select an existing account to fund it. 5. Click Open New Account. | F18: Type: SAVINGS | G18: Message "Account Opened!" with the new account number should be displayed. | H18: "Account Opened!" and a new account number were displayed. | I18: Pass
A19: 18 | B19: TC_018 | C19: Open New Account | D19: Verify that the newly opened account appears in Accounts Overview. | E19: 1. Login. 2. Open a new account and note the account number. 3. Open Accounts Overview. | F19: Type: SAVINGS | G19: The new account should be listed in Accounts Overview. | H19: The new account was listed in Accounts Overview. | I19: Pass
A20: 19 | B20: TC_019 | C20: Transfer Funds | D20: Verify that funds can be transferred between two accounts. | E20: 1. Login. 2. Click Transfer Funds. 3. Enter amount. 4. Select From and To accounts. 5. Click Transfer. | F20: Amount: 100 From/To: two different accounts | G20: "Transfer Complete!" message with amount and account numbers should be displayed. | H20: "Transfer Complete!" message was displayed with correct details. | I20: Pass
A21: 20 | B21: TC_020 | C21: Transfer Funds | D21: Verify that an error is displayed when the transfer amount is blank. | E21: 1. Login. 2. Open Transfer Funds. 3. Leave Amount blank. 4. Click Transfer. | F21: Amount: Blank | G21: Message "The amount cannot be empty." should be displayed. | H21: Message "The amount cannot be empty." was displayed. | I21: Pass
A22: 21 | B22: TC_021 | C22: Transfer Funds | D22: Verify that a non-numeric transfer amount is rejected. | E22: 1. Login. 2. Open Transfer Funds. 3. Enter letters in Amount. 4. Click Transfer. | F22: Amount: abc | G22: A validation message should be displayed and no transfer should happen. | H22: System accepted non-numeric characters in transfer amount, causing an unhandled server error. | I22: Fail | J22: BUG_003
A23: 22 | B23: TC_022 | C23: Transfer Funds | D23: Verify that a transfer greater than the available balance is handled correctly. | E23: 1. Login. 2. Open Transfer Funds. 3. Enter an amount greater than the From account balance. 4. Click Transfer. | F23: Amount: more than available balance | G23: Transfer should be rejected with an insufficient-funds message. | H23: Transfer was rejected and appropriate error message was displayed. | I23: Pass
A24: 23 | B24: TC_023 | C24: Transfer Funds | D24: Verify that account balances are updated after a transfer. | E24: 1. Login and note both account balances. 2. Transfer 100 from account A to account B. 3. Open Accounts Overview. | F24: Amount: 100 | G24: Account A should decrease by 100 and account B should increase by 100. | H24: Balances were updated correctly. | I24: Pass
A25: 24 | B25: TC_024 | C25: Bill Pay | D25: Verify that a bill payment can be made with valid payee details. | E25: 1. Login. 2. Click Bill Pay. 3. Enter payee details, account number (twice) and amount. 4. Select From account. 5. Click Send Payment. | F25: Payee: Electric Co Address: 5 Park St City: Mumbai State: MH Zip: 400001 Phone: 9876543210 Account: 12345 (confirm 12345) Amount: 50 | G25: "Bill Payment Complete" message should be displayed with payee, amount and account. | H25: "Bill Payment Complete" was displayed with correct details. | I25: Pass
A26: 25 | B26: TC_025 | C26: Bill Pay | D26: Verify that validation messages are displayed when Bill Pay fields are blank. | E26: 1. Login. 2. Open Bill Pay. 3. Leave all fields blank. 4. Click Send Payment. | F26: All fields blank | G26: Required-field messages should be displayed for all mandatory fields. | H26: Required-field messages were displayed. | I26: Pass
A27: 26 | B27: TC_026 | C27: Bill Pay | D27: Verify that an error is displayed when the account numbers do not match. | E27: 1. Login. 2. Open Bill Pay. 3. Enter different Account and Verify Account numbers. 4. Fill other fields. 5. Click Send Payment. | F27: Account: 12345 Verify: 54321 | G27: Message "The account numbers do not match." should be displayed. | H27: Account number mismatch message was displayed. | I27: Pass
A28: 27 | B28: TC_027 | C28: Find Transactions | D28: Verify that a transaction can be found by Transaction ID. | E28: 1. Login. 2. Click Find Transactions. 3. Select account. 4. Enter a valid Transaction ID. 5. Click Find Transactions. | F28: Transaction ID: from account activity | G28: The matching transaction should be displayed. | H28: The matching transaction was displayed. | I28: Pass
A29: 28 | B29: TC_028 | C29: Find Transactions | D29: Verify that transactions can be found by amount. | E29: 1. Login. 2. Open Find Transactions. 3. Select account. 4. Enter the amount of a known transaction. 5. Click Find Transactions. | F29: Amount: 100 | G29: Transactions with the entered amount should be listed. | H29: Transactions with the entered amount were listed. | I29: Pass
A30: 29 | B30: TC_029 | C30: Find Transactions | D30: Verify that transactions can be found by date. | E30: 1. Login. 2. Open Find Transactions. 3. Select account. 4. Enter today's date in Find by Date. 5. Click Find Transactions. | F30: Date: today (MM-DD-YYYY) | G30: Transactions made on that date should be listed. | H30: Transactions made on that date were listed. | I30: Pass
A31: 30 | B31: TC_030 | C31: Find Transactions | D31: Verify that an error is displayed when the Transaction ID field is blank or invalid. | E31: 1. Login. 2. Open Find Transactions. 3. Leave Transaction ID blank or enter letters. 4. Click Find Transactions. | F31: Transaction ID: Blank / abc | G31: Validation message should be displayed. | H31: System displayed an internal server error page when submitting invalid/blank Transaction ID. | I31: Fail | J31: BUG_004
A32: 31 | B32: TC_031 | C32: Update Contact Info | D32: Verify that the user can update contact information. | E32: 1. Login. 2. Click Update Contact Info. 3. Change the Phone Number. 4. Click Update Profile. | F32: Phone: 9123456780 | G32: "Profile Updated" message should be displayed. | H32: "Profile Updated" message was displayed. | I32: Pass
A33: 32 | B33: TC_032 | C33: Update Contact Info | D33: Verify that validation messages are displayed when required profile fields are blank. | E33: 1. Login. 2. Open Update Contact Info. 3. Clear First Name and Address. 4. Click Update Profile. | F33: First Name: Blank Address: Blank | G33: Required-field messages should be displayed. | H33: Required-field messages were displayed. | I33: Pass
A34: 33 | B34: TC_033 | C34: Request Loan | D34: Verify that a loan request is processed with valid loan and down payment amounts. | E34: 1. Login. 2. Click Request Loan. 3. Enter loan amount and down payment. 4. Select From account. 5. Click Apply Now. | F34: Loan Amount: 1000 Down Payment: 100 | G34: "Loan Request Processed" should be displayed with an Approved or Denied status. | H34: Loan result page was displayed with a status. | I34: Pass
A35: 34 | B35: TC_034 | C35: Request Loan | D35: Verify that a loan request with blank amount and down payment is rejected. | E35: 1. Login. 2. Open Request Loan. 3. Leave Loan Amount and Down Payment blank. 4. Click Apply Now. | F35: Loan Amount: Blank Down Payment: Blank | G35: A validation message should be displayed and no loan should be processed. | H35: Validation message was displayed and blank request was rejected. | I35: Pass
A36: 35 | B36: TC_035 | C36: Logout | D36: Verify that the user can log out successfully. | E36: 1. Login. 2. Click Log Out. | F36: Username: <your registered username> Password: <your password> | G36: User should be logged out and the Customer Login page should be displayed. | H36: Customer Login page was displayed. | I36: Pass
A37: 36 | B37: TC_036 | C37: Logout | D37: Verify that the user can log in again after logout. | E37: 1. Login. 2. Log out. 3. Login again with valid credentials. | F37: Username: <your registered username> Password: <your password> | G37: User should log in again and Accounts Overview should open. | H37: Accounts Overview was displayed. | I37: Pass

Sheet DefectReport
A1: Bug ID | B1: Test Case ID | C1: Module | D1: Bug Summary | E1: Severity | F1: Priority | G1: Status | H1: Steps to Reproduce | I1: Expected Result | J1: Actual Result
A2: BUG_001 | B2: TC_012 | C2: Security | D2: Session ID is exposed in page URLs (;jsessionid=...) | E2: Medium | F2: Medium | G2: Open | H2: 1. Open application URL. 2. Click any link (About Us, Services, Register). 3. Check browser address bar. | I2: URLs should not contain session ID; session should be managed via secure HTTP-only cookies. | J2: Links and page URLs contain ";jsessionid=<value>", exposing sensitive session identifiers.
A3: BUG_002 | B3: TC_013 | C3: Security | D3: Account pages accessible via browser Back button after logout | E3: High | F3: High | G3: Open | H3: 1. Log into ParaBank application. 2. Click Log Out. 3. Click browser Back button. | I3: Session should be destroyed upon logout, and previous pages should fail authentication. | J3: User can view previous account summary and transaction details without re-authenticating.
A4: BUG_003 | B4: TC_021 | C4: Transfer Funds | D4: Unhandled Exception / HTTP 500 error on entering non-numeric transfer amount | E4: High | F4: Medium | G4: Open | H4: 1. Log in and go to Transfer Funds. 2. Enter non-numeric text (e.g., "abc") in Amount. 3. Click Transfer. | I4: Client/Server side validation should trigger a clear error message: "Please enter a valid amount". | J4: Application crashes with an unhandled exception page (HTTP 500 / NumberFormatException).
A5: BUG_004 | B5: TC_030 | C5: Find Transactions | D5: Internal Error page displayed when Find Transactions search criteria is blank or invalid | E5: Medium | F5: Medium | G5: Open | H5: 1. Go to Find Transactions. 2. Leave Transaction ID blank or enter special characters. 3. Click Find Transactions. | I5: Validation error message should prompt user to enter valid search criteria. | J5: An empty search triggers an raw error stack trace on the webpage.

Sheet SummaryReport
A1: PARABANK MANUAL TESTING - EXECUTIVE SUMMARY REPORT
A2: Overall Execution Status & Defect Breakdown
A4: Total Test Cases | B4: Executed | C4: Passed | D4: Failed | E4: Pass Rate (%) | F4: Total Bugs Found
A5: =COUNTA(TestCase!B2:B37) -> 36 | B5: =COUNTIF(TestCase!I2:I37,"Pass")+COUNTIF(TestCase!I2:I37,"Fail") -> 36 | C5: =COUNTIF(TestCase!I2:I37,"Pass") -> 32 | D5: =COUNTIF(TestCase!I2:I37,"Fail") -> 4 | E5: =C5/B5 -> 0.88888889 | F5: =COUNTA(DefectReport!A2:A5) -> 4
A7: Module-wise Test Execution Summary
A8: Module Name | B8: Total Test Cases | C8: Executed | D8: Passed | E8: Failed | F8: Module Pass Rate (%)
A9: Registration | B9: =COUNTIF(TestCase!$C$2:$C$37, "Registration") -> 5 | C9: =COUNTIFS(TestCase!$C$2:$C$37, "Registration", TestCase!$I$2:$I$37, "Pass") + COUNTIFS(TestCase!$C$2:$C$37, "Registration", TestCase!$I$2:$I$37, "Fail") -> 5 | D9: =COUNTIFS(TestCase!$C$2:$C$37, "Registration", TestCase!$I$2:$I$37, "Pass") -> 5 | E9: =COUNTIFS(TestCase!$C$2:$C$37, "Registration", TestCase!$I$2:$I$37, "Fail") -> 0 | F9: =IF(C9>0, D9/C9, 0) -> 1
A10: Login | B10: =COUNTIF(TestCase!$C$2:$C$37, "Login") -> 6 | C10: =COUNTIFS(TestCase!$C$2:$C$37, "Login", TestCase!$I$2:$I$37, "Pass") + COUNTIFS(TestCase!$C$2:$C$37, "Login", TestCase!$I$2:$I$37, "Fail") -> 6 | D10: =COUNTIFS(TestCase!$C$2:$C$37, "Login", TestCase!$I$2:$I$37, "Pass") -> 6 | E10: =COUNTIFS(TestCase!$C$2:$C$37, "Login", TestCase!$I$2:$I$37, "Fail") -> 0 | F10: =IF(C10>0, D10/C10, 0) -> 1
A11: Security | B11: =COUNTIF(TestCase!$C$2:$C$37, "Security") -> 2 | C11: =COUNTIFS(TestCase!$C$2:$C$37, "Security", TestCase!$I$2:$I$37, "Pass") + COUNTIFS(TestCase!$C$2:$C$37, "Security", TestCase!$I$2:$I$37, "Fail") -> 2 | D11: =COUNTIFS(TestCase!$C$2:$C$37, "Security", TestCase!$I$2:$I$37, "Pass") -> 0 | E11: =COUNTIFS(TestCase!$C$2:$C$37, "Security", TestCase!$I$2:$I$37, "Fail") -> 2 | F11: =IF(C11>0, D11/C11, 0) -> 0
A12: Accounts Overview | B12: =COUNTIF(TestCase!$C$2:$C$37, "Accounts Overview") -> 2 | C12: =COUNTIFS(TestCase!$C$2:$C$37, "Accounts Overview", TestCase!$I$2:$I$37, "Pass") + COUNTIFS(TestCase!$C$2:$C$37, "Accounts Overview", TestCase!$I$2:$I$37, "Fail") -> 2 | D12: =COUNTIFS(TestCase!$C$2:$C$37, "Accounts Overview", TestCase!$I$2:$I$37, "Pass") -> 2 | E12: =COUNTIFS(TestCase!$C$2:$C$37, "Accounts Overview", TestCase!$I$2:$I$37, "Fail") -> 0 | F12: =IF(C12>0, D12/C12, 0) -> 1
A13: Open New Account | B13: =COUNTIF(TestCase!$C$2:$C$37, "Open New Account") -> 3 | C13: =COUNTIFS(TestCase!$C$2:$C$37, "Open New Account", TestCase!$I$2:$I$37, "Pass") + COUNTIFS(TestCase!$C$2:$C$37, "Open New Account", TestCase!$I$2:$I$37, "Fail") -> 3 | D13: =COUNTIFS(TestCase!$C$2:$C$37, "Open New Account", TestCase!$I$2:$I$37, "Pass") -> 3 | E13: =COUNTIFS(TestCase!$C$2:$C$37, "Open New Account", TestCase!$I$2:$I$37, "Fail") -> 0 | F13: =IF(C13>0, D13/C13, 0) -> 1
A14: Transfer Funds | B14: =COUNTIF(TestCase!$C$2:$C$37, "Transfer Funds") -> 5 | C14: =COUNTIFS(TestCase!$C$2:$C$37, "Transfer Funds", TestCase!$I$2:$I$37, "Pass") + COUNTIFS(TestCase!$C$2:$C$37, "Transfer Funds", TestCase!$I$2:$I$37, "Fail") -> 5 | D14: =COUNTIFS(TestCase!$C$2:$C$37, "Transfer Funds", TestCase!$I$2:$I$37, "Pass") -> 4 | E14: =COUNTIFS(TestCase!$C$2:$C$37, "Transfer Funds", TestCase!$I$2:$I$37, "Fail") -> 1 | F14: =IF(C14>0, D14/C14, 0) -> 0.8
A15: Bill Pay | B15: =COUNTIF(TestCase!$C$2:$C$37, "Bill Pay") -> 3 | C15: =COUNTIFS(TestCase!$C$2:$C$37, "Bill Pay", TestCase!$I$2:$I$37, "Pass") + COUNTIFS(TestCase!$C$2:$C$37, "Bill Pay", TestCase!$I$2:$I$37, "Fail") -> 3 | D15: =COUNTIFS(TestCase!$C$2:$C$37, "Bill Pay", TestCase!$I$2:$I$37, "Pass") -> 3 | E15: =COUNTIFS(TestCase!$C$2:$C$37, "Bill Pay", TestCase!$I$2:$I$37, "Fail") -> 0 | F15: =IF(C15>0, D15/C15, 0) -> 1
A16: Find Transactions | B16: =COUNTIF(TestCase!$C$2:$C$37, "Find Transactions") -> 4 | C16: =COUNTIFS(TestCase!$C$2:$C$37, "Find Transactions", TestCase!$I$2:$I$37, "Pass") + COUNTIFS(TestCase!$C$2:$C$37, "Find Transactions", TestCase!$I$2:$I$37, "Fail") -> 4 | D16: =COUNTIFS(TestCase!$C$2:$C$37, "Find Transactions", TestCase!$I$2:$I$37, "Pass") -> 3 | E16: =COUNTIFS(TestCase!$C$2:$C$37, "Find Transactions", TestCase!$I$2:$I$37, "Fail") -> 1 | F16: =IF(C16>0, D16/C16, 0) -> 0.75
A17: Update Contact Info | B17: =COUNTIF(TestCase!$C$2:$C$37, "Update Contact Info") -> 2 | C17: =COUNTIFS(TestCase!$C$2:$C$37, "Update Contact Info", TestCase!$I$2:$I$37, "Pass") + COUNTIFS(TestCase!$C$2:$C$37, "Update Contact Info", TestCase!$I$2:$I$37, "Fail") -> 2 | D17: =COUNTIFS(TestCase!$C$2:$C$37, "Update Contact Info", TestCase!$I$2:$I$37, "Pass") -> 2 | E17: =COUNTIFS(TestCase!$C$2:$C$37, "Update Contact Info", TestCase!$I$2:$I$37, "Fail") -> 0 | F17: =IF(C17>0, D17/C17, 0) -> 1
A18: Request Loan | B18: =COUNTIF(TestCase!$C$2:$C$37, "Request Loan") -> 2 | C18: =COUNTIFS(TestCase!$C$2:$C$37, "Request Loan", TestCase!$I$2:$I$37, "Pass") + COUNTIFS(TestCase!$C$2:$C$37, "Request Loan", TestCase!$I$2:$I$37, "Fail") -> 2 | D18: =COUNTIFS(TestCase!$C$2:$C$37, "Request Loan", TestCase!$I$2:$I$37, "Pass") -> 2 | E18: =COUNTIFS(TestCase!$C$2:$C$37, "Request Loan", TestCase!$I$2:$I$37, "Fail") -> 0 | F18: =IF(C18>0, D18/C18, 0) -> 1
A19: Logout | B19: =COUNTIF(TestCase!$C$2:$C$37, "Logout") -> 2 | C19: =COUNTIFS(TestCase!$C$2:$C$37, "Logout", TestCase!$I$2:$I$37, "Pass") + COUNTIFS(TestCase!$C$2:$C$37, "Logout", TestCase!$I$2:$I$37, "Fail") -> 2 | D19: =COUNTIFS(TestCase!$C$2:$C$37, "Logout", TestCase!$I$2:$I$37, "Pass") -> 2 | E19: =COUNTIFS(TestCase!$C$2:$C$37, "Logout", TestCase!$I$2:$I$37, "Fail") -> 0 | F19: =IF(C19>0, D19/C19, 0) -> 1
A20: Total | B20: =SUM(B9:B19) -> 36 | C20: =SUM(C9:C19) -> 36 | D20: =SUM(D9:D19) -> 32 | E20: =SUM(E9:E19) -> 4 | F20: =D20/C20 -> 0.88888889
A22: Defect Summary Breakdown
A23: Severity | B23: Count | D23: Priority | E23: Count
A24: High | B24: =COUNTIF(DefectReport!$E$2:$E$5, "High") -> 2 | D24: High | E24: =COUNTIF(DefectReport!$F$2:$F$5, "High") -> 1
A25: Medium | B25: =COUNTIF(DefectReport!$E$2:$E$5, "Medium") -> 2 | D25: Medium | E25: =COUNTIF(DefectReport!$F$2:$F$5, "Medium") -> 3
A26: Low | B26: =COUNTIF(DefectReport!$E$2:$E$5, "Low") -> 0 | D26: Low | E26: =COUNTIF(DefectReport!$F$2:$F$5, "Low") -> 0
A27: Total Defects | B27: =SUM(B24:B26) -> 4 | D27: Total Defects | E27: =SUM(E24:E26) -> 4

Sheet RTM
A1: Requirements Traceability Matrix (RTM)
A2: Application: ParaBank | Prepared By: Gautami Mahajan | Testing Type: Manual Testing
A4: Req ID | B4: Requirement Description | C4: Module | D4: Test Scenario ID | E4: Test Case ID | F4: Test Case Description | G4: Execution Status
A5: REQ-001 | B5: User must be able to register with valid details | C5: Registration | D5: TS-001 | E5: TC_001 | F5: Verify a new user can register successfully with valid details. | G5: =TestCase!I2 -> Pass
A6: REQ-002 | B6: Mandatory registration fields must be validated | C6: Registration | D6: TS-002 | E6: TC_002 | F6: Verify validation messages are displayed when all registration fields are left blank. | G6: =TestCase!I3 -> Pass
A7: REQ-003 | B7: Password and Confirm Password must match | C7: Registration | D7: TS-003 | E7: TC_003 | F7: Verify registration fails when Password and Confirm Password do not match. | G7: =TestCase!I4 -> Pass
A8: REQ-004 | B8: Duplicate usernames must be rejected | C8: Registration | D8: TS-004 | E8: TC_004 | F8: Verify registration fails when the username already exists. | G8: =TestCase!I5 -> Pass
A9: REQ-002 | B9: Mandatory registration fields must be validated | C9: Registration | D9: TS-005 | E9: TC_005 | F9: Verify Username is mandatory on the Register page. | G9: =TestCase!I6 -> Pass
A10: REQ-005 | B10: User must be able to login with valid credentials | C10: Login | D10: TS-006 | E10: TC_006 | F10: Verify the user can log in successfully with valid credentials. | G10: =TestCase!I7 -> Pass
A11: REQ-006 | B11: System must show an error for invalid credentials | C11: Login | D11: TS-007 | E11: TC_007 | F11: Verify an error is displayed when an invalid username and password are entered. | G11: =TestCase!I8 -> Pass
A12: REQ-007 | B12: System must show a message when login fields are blank | C12: Login | D12: TS-008 | E12: TC_008 | F12: Verify an error is displayed when Username and Password are left blank. | G12: =TestCase!I9 -> Pass
A13: REQ-008 | B13: Password field must mask the entered text | C13: Login | D13: TS-009 | E13: TC_009 | F13: Verify the Password field masks the entered characters. | G13: =TestCase!I10 -> Pass
A14: REQ-009 | B14: User must be able to retrieve login info | C14: Login | D14: TS-010 | E14: TC_010 | F14: Verify a registered user can retrieve login info using the Forgot login info link. | G14: =TestCase!I11 -> Pass
A15: REQ-010 | B15: Forgot login info fields must be validated | C15: Login | D15: TS-011 | E15: TC_011 | F15: Verify validation messages are displayed on the Forgot login info page when fields are blank. | G15: =TestCase!I12 -> Pass
A16: REQ-011 | B16: Session ID must not be exposed in the URL | C16: Security | D16: TS-012 | E16: TC_012 | F16: Verify the session ID is not exposed in the page URL. | G16: =TestCase!I13 -> Fail
... A40: REQ-030 | B40: User must be able to login again after logout | C40: Logout | D40: TS-036 | E40: TC_036 | F40: Verify the user can log in again after logout. | G40: =TestCase!I37 -> Pass
A42: Test Execution Summary
A43: Total Test Cases | C43: =COUNTA(E5:E40) -> 36
A44: Passed | C44: =COUNTIF(G5:G40,"Pass") -> 32
A45: Failed | C45: =COUNTIF(G5:G40,"Fail") -> 4
A46: Executed | C46: =COUNTA(G5:G40) -> 36
